sopel_iplookup/__init__.py
sopel_iplookup/config.py
sopel_iplookup/plugin.py
sopel_iplookup-1.1.0.dist-info/LICENSE.txt
sopel_iplookup-1.1.0.dist-info/METADATA
sopel_iplookup-1.1.0.dist-info/WHEEL
sopel_iplookup-1.1.0.dist-info/entry_points.txt
sopel_iplookup-1.1.0.dist-info/top_level.txt
sopel_iplookup-1.1.0.dist-info/RECORD
