Metadata-Version: 2.1
Name: sopel-iplookup
Version: 1.1.0
Summary: IP Lookup plugin for Sopel
Author: Dimitri Molenaars
Author-email: Elad Alfassa <elad@fedoraproject.org>, dgw <dgw@technobabbl.es>, Florian Strzelecki <florian.strzelecki@gmail.com>, SnoopJ <snoopjedi@gmail.com>
Maintainer-email: dgw <dgw@technobabbl.es>, Florian Strzelecki <florian.strzelecki@gmail.com>, SnoopJ <snoopjedi@gmail.com>
License: EFL-2.0
Project-URL: Homepage, https://github.com/sopel-irc/sopel-iplookup
Project-URL: Bug Tracker, https://github.com/sopel-irc/sopel-iplookup/issues
Keywords: sopel,plugin,bot,irc
Platform: Linux x86, x86-64
Classifier: Development Status :: 4 - Beta
Classifier: Intended Audience :: Developers
Classifier: Intended Audience :: System Administrators
Classifier: License :: Eiffel Forum License (EFL)
Classifier: License :: OSI Approved :: Eiffel Forum License
Classifier: Operating System :: POSIX :: Linux
Classifier: Programming Language :: Python :: 3.7
Classifier: Programming Language :: Python :: 3.8
Classifier: Programming Language :: Python :: 3.9
Classifier: Programming Language :: Python :: 3.10
Classifier: Programming Language :: Python :: 3.11
Classifier: Topic :: Communications :: Chat :: Internet Relay Chat
Requires-Python: <4,>=3.7
License-File: LICENSE.txt
Requires-Dist: sopel >=7.1
Requires-Dist: geoip2
